jsonabc/__init__.py
jsonabc/_base.py
jsonabc-0.0.3.dist-info/LICENSE
jsonabc-0.0.3.dist-info/METADATA
jsonabc-0.0.3.dist-info/WHEEL
jsonabc-0.0.3.dist-info/top_level.txt
jsonabc-0.0.3.dist-info/RECORD
