Metadata-Version: 2.1
Name: jsonabc
Version: 0.0.3
Summary: Minimal, pythonic JSON to class serializer with zero dependencies and types validation.
Home-page: https://github.com/adhaamehab/jsonabc
Author: Adham Ehab
Author-email: adhaamehab.me@gmail.com
Classifier: Programming Language :: Python :: 3
Classifier: License :: OSI Approved :: Apache Software License
Classifier: Operating System :: OS Independent
Requires-Python: >=3.9
License-File: LICENSE
